postdmarc/__init__.py
postdmarc/pdm_exceptions.py
postdmarc/postdmarc.py
tests/__init__.py
tests/test_meta.py
tests/test_postdmarc.py
py_postdmarc-0.0.1.dist-info/METADATA
py_postdmarc-0.0.1.dist-info/WHEEL
py_postdmarc-0.0.1.dist-info/entry_points.txt
py_postdmarc-0.0.1.dist-info/license.txt
py_postdmarc-0.0.1.dist-info/top_level.txt
py_postdmarc-0.0.1.dist-info/RECORD
