Metadata-Version: 2.1
Name: py-postdmarc
Version: 0.0.1
Summary: A Python CLI interface for the Postmark DMARC monitoring API
Home-page: https://github.com/scuriosity/py-postdmarc
Author: Andrew Simon
Author-email: asimon1@protonmail.com
License: MIT
Keywords: dmarc postmark forensic report
Platform: UNKNOWN
Requires-Dist: dateparser (<1.0,>=0.7)
Requires-Dist: requests (<3.0,>=2.0.0)
Requires-Dist: fire (>=0.3)
